phovea_clue/__init__.py
phovea_clue/config.json
phovea_clue/remoteplayer.py
phovea_clue-9.0.0.dist-info/LICENSE
phovea_clue-9.0.0.dist-info/METADATA
phovea_clue-9.0.0.dist-info/WHEEL
phovea_clue-9.0.0.dist-info/entry_points.txt
phovea_clue-9.0.0.dist-info/top_level.txt
phovea_clue-9.0.0.dist-info/RECORD
