Metadata-Version: 2.1
Name: phovea-clue
Version: 9.0.0
Summary: DEPRECATED: The foundation for Vistories: CLUE playground for provenance storage and visualization
Home-page: http://vistories.org
Author: The Caleydo Team
Author-email: contact@caleydo.org
License: BSD-3-Clause
Platform: UNKNOWN
Classifier: Intended Audience :: Developers
Classifier: Operating System :: OS Independent
Classifier: License :: OSI Approved :: BSD License
Classifier: Programming Language :: Python
Classifier: Programming Language :: Python :: 3.7
License-File: LICENSE
Requires-Dist: python-memcached (==1.59)
Requires-Dist: phovea-server (<8.0.0,>=7.2.0)
Requires-Dist: phovea-security-flask (<10.0.0,>=9.0.0)
